wmill/__init__.py
wmill/client.py
wmill/py.typed
wmill/s3_reader.py
wmill/s3_types.py
alex_wmill-1.440.0.dist-info/METADATA
alex_wmill-1.440.0.dist-info/WHEEL
alex_wmill-1.440.0.dist-info/RECORD
