Metadata-Version: 2.1
Name: alex_wmill
Version: 1.440.0
Summary: A client library for accessing Windmill server wrapping the Windmill client API
Home-page: https://windmill.dev
License: Apache-2.0
Author: Ruben Fiszel
Author-email: ruben@windmill.dev
Requires-Python: >=3.7,<4.0
Classifier: License :: OSI Approved :: Apache Software License
Classifier: Programming Language :: Python :: 3
Classifier: Programming Language :: Python :: 3.7
Classifier: Programming Language :: Python :: 3.8
Classifier: Programming Language :: Python :: 3.9
Classifier: Programming Language :: Python :: 3.10
Classifier: Programming Language :: Python :: 3.11
Classifier: Programming Language :: Python :: 3.12
Classifier: Programming Language :: Python :: 3.13
Requires-Dist: httpx (>=0.24)
Requires-Dist: slack-sdk (>=3.33.5,<4.0.0)
Project-URL: Documentation, https://windmill.dev
